logged_requests
