Metadata-Version: 1.1
Name: logged-requests
Version: 0.4
Summary: Simple wrapper around the requets library
Home-page: https://github.com/josuebrunel/logged-requests
Author: Josue Kouka
Author-email: josuebrunel@gmail.com
License: MIT
Download-URL: https://github.com/josuebrunel/logged-requests/archive/0.4.tar.gz
Keywords: requests,logging,log,logger,logged requests
Platform: Any
Classifier: Programming Language :: Python
Classifier: Programming Language :: Python :: 2
Classifier: Programming Language :: Python :: 2.7
Classifier: Programming Language :: Python :: 3
Classifier: Programming Language :: Python :: 3.3
Classifier: Programming Language :: Python :: 3.4
Classifier: Programming Language :: Python :: 3.5
Classifier: Programming Language :: Python :: Implementation :: CPython
Classifier: Programming Language :: Python :: Implementation :: PyPy
Classifier: Development Status :: 5 - Production/Stable
Classifier: Topic :: Software Development :: Libraries :: Python Modules
Classifier: Environment :: Console
Classifier: Intended Audience :: Developers
Classifier: License :: OSI Approved :: MIT License
